{"routes": [{"directions": [{"tag": "22___O_F00", "name": "Outbound", "title": "Outbound to Third + 20th Streets"}, {"tag": "22___I_F00", "name": "Inbound", "title": "Inbound to Bay Street"}], "tag": "22", "stop": "3343", "title": "22-Fillmore"}, {"directions": [{"tag": "22___O_F00", "name": "Outbound", "title": "Outbound to Third + 20th Streets"}, {"tag": "22___I_F00", "name": "Inbound", "title": "Inbound to Bay Street"}], "tag": "22", "stop": "3342", "title": "22-Fillmore"}, {"directions": [{"tag": "22___O_F00", "name": "Outbound", "title": "Outbound to Third + 20th Streets"}, {"tag": "22___I_F00", "name": "Inbound", "title": "Inbound to Bay Street"}], "tag": "22", "stop": "3337", "title": "22-Fillmore"}, {"directions": [{"tag": "55___I_F00", "name": "Inbound", "title": "Inbound to Mission Street / BART"}, {"tag": "55___O_F01", "name": "Outbound", "title": "Outbound to UCSF Mission Bay"}], "tag": "55", "stop": "7767", "title": "55-16th Street"}, {"directions": [{"tag": "55___I_F00", "name": "Inbound", "title": "Inbound to Mission Street / BART"}, {"tag": "55___O_F01", "name": "Outbound", "title": "Outbound to UCSF Mission Bay"}], "tag": "55", "stop": "7865", "title": "55-16th Street"}, {"directions": [{"tag": "22___O_F00", "name": "Outbound", "title": "Outbound to Third + 20th Streets"}, {"tag": "22___I_F00", "name": "Inbound", "title": "Inbound to Bay Street"}], "tag": "22", "stop": "3347", "title": "22-Fillmore"}, {"directions": [{"tag": "55___I_F00", "name": "Inbound", "title": "Inbound to Mission Street / BART"}, {"tag": "55___O_F01", "name": "Outbound", "title": "Outbound to UCSF Mission Bay"}], "tag": "55", "stop": "7866", "title": "55-16th Street"}, {"directions": [{"tag": "22___O_F00", "name": "Outbound", "title": "Outbound to Third + 20th Streets"}, {"tag": "22___I_F00", "name": "Inbound", "title": "Inbound to Bay Street"}], "tag": "22", "stop": "3346", "title": "22-Fillmore"}]}