{"routes": [{"directions": [{"tag": "28___O_F00", "name": "Outbound", "title": "Outbound to Daly City BART"}, {"tag": "28___I_F00", "name": "Inbound", "title": "Inbound to North Point + Van Ness"}], "tag": "28", "stop": "14773", "title": "28-19th Avenue"}, {"directions": [{"tag": "76X__O_F00", "name": "Outbound", "title": "Outbound to Marin Headlands"}, {"tag": "76X__I_F00", "name": "Inbound", "title": "Inbound to Downtown S.F."}], "tag": "76X", "stop": "4778", "title": "76X-Marin Headlands Express"}]}