{"routes": [{"directions": [{"tag": "M____O_D00", "name": "Outbound", "title": "Outbound to Balboa Park Station via S.F. State"}, {"tag": "M____I_L73", "name": "Inbound", "title": "Inbound to Embarcadero"}], "tag": "M", "stop": "3387", "title": "M-Ocean View"}, {"directions": [{"tag": "54___O_F00", "name": "Outbound", "title": "Outbound to Daly City BART"}, {"tag": "54___I_F00", "name": "Inbound", "title": "Inbound to Bayview District"}], "tag": "54", "stop": "3628", "title": "54-Felton"}, {"directions": [{"tag": "28___O_F00", "name": "Outbound", "title": "Outbound to Daly City BART"}, {"tag": "28___I_F00", "name": "Inbound", "title": "Inbound to North Point + Van Ness"}], "tag": "28", "stop": "5134", "title": "28-19th Avenue"}, {"directions": [{"tag": "M____O_N00", "name": "Outbound", "title": "Outbound to Balboa Park"}, {"tag": "M____I_N00", "name": "Inbound", "title": "Inbound to Ferry Plaza"}], "tag": "M_OWL", "stop": "3385", "title": "M-Owl"}, {"directions": [{"tag": "57___I_F00", "name": "Inbound", "title": "Inbound to West Portal Station"}, {"tag": "57___O_F00", "name": "Outbound", "title": "Outbound to Lakeshore Plaza"}], "tag": "57", "stop": "5135", "title": "57-Parkmerced"}, {"directions": [{"tag": "57___I_F00", "name": "Inbound", "title": "Inbound to West Portal Station"}, {"tag": "57___O_F00", "name": "Outbound", "title": "Outbound to Lakeshore Plaza"}], "tag": "57", "stop": "5140", "title": "57-Parkmerced"}, {"directions": [{"tag": "54___O_F00", "name": "Outbound", "title": "Outbound to Daly City BART"}, {"tag": "54___I_F00", "name": "Inbound", "title": "Inbound to Bayview District"}], "tag": "54", "stop": "6484", "title": "54-Felton"}, {"directions": [{"tag": "28___O_F00", "name": "Outbound", "title": "Outbound to Daly City BART"}, {"tag": "28___I_F00", "name": "Inbound", "title": "Inbound to North Point + Van Ness"}], "tag": "28", "stop": "5140", "title": "28-19th Avenue"}, {"directions": [{"tag": "28___O_F00", "name": "Outbound", "title": "Outbound to Daly City BART"}, {"tag": "28___I_F00", "name": "Inbound", "title": "Inbound to North Point + Van Ness"}], "tag": "28", "stop": "5135", "title": "28-19th Avenue"}, {"directions": [{"tag": "M____O_D00", "name": "Outbound", "title": "Outbound to Balboa Park Station via S.F. State"}, {"tag": "M____I_L73", "name": "Inbound", "title": "Inbound to Embarcadero"}], "tag": "M", "stop": "3385", "title": "M-Ocean View"}, {"directions": [{"tag": "57___I_F00", "name": "Inbound", "title": "Inbound to West Portal Station"}, {"tag": "57___O_F00", "name": "Outbound", "title": "Outbound to Lakeshore Plaza"}], "tag": "57", "stop": "15140", "title": "57-Parkmerced"}]}